{"config": {"view": {"continuousWidth": 400, "continuousHeight": 300}}, "data": {"url": "https://cdn.jsdelivr.net/npm/vega-datasets@v1.29.0/data/us-10m.json", "format": {"feature": "states", "type": "topojson"}}, "mark": "geoshape", "encoding": {"color": {"type": "quantitative", "field": "value"}, "tooltip": [{"type": "ordinal", "field": "state_abbr"}, {"type": "quantitative", "field": "value"}]}, "height": 300, "projection": {"type": "albersUsa"}, "resolve": {"scale": {"color": "independent"}}, "selection": {"SLEPTIM": {"type": "single", "fields": ["variable"], "bind": {"input": "select", "options": ["SLEPTIM_2009", "SLEPTIM_2020", "resid_chng"]}, "init": {"variable": "resid_chng"}}}, "title": "Sleep amount", "transform": [{"lookup": "id", "from": {"data": {"name": "data-8108860f4c00a679c8bccccaed25f671"}, "key": "state_id", "fields": ["state_abbr", "SLEPTIM_2009", "SLEPTIM_2020", "resid_chng"]}}, {"fold": ["SLEPTIM_2009", "SLEPTIM_2020", "resid_chng"], "as": ["variable", "value"]}, {"filter": {"selection": "SLEPTIM"}}], "width": 500, "$schema": "https://vega.github.io/schema/vega-lite/v4.8.1.json", "datasets": {"data-8108860f4c00a679c8bccccaed25f671": [{"state_id": 13, "state_abbr": "GA", "SLEPTIM_2009": 7.044415775893844, "resid_2009": -0.004418206912384318, "SLEPTIM_2020": 7.059608540925267, "resid_2020": 0.007352961043062574, "var_chng": 0.015192765031422972, "resid_chng": 0.011771167955446893}, {"state_id": 15, "state_abbr": "HI", "SLEPTIM_2009": 6.863470969783262, "resid_2009": -0.11842348533201753, "SLEPTIM_2020": 6.847519582245431, "resid_2020": -0.12622743882167425, "var_chng": -0.01595138753783143, "resid_chng": -0.00780395348965672}, {"state_id": 17, "state_abbr": "IL", "SLEPTIM_2009": 7.011137057661218, "resid_2009": -0.03684398271262987, "SLEPTIM_2020": 7.096949891067538, "resid_2020": 0.027066313866950263, "var_chng": 0.08581283340632062, "resid_chng": 0.06391029657958014}, {"state_id": 22, "state_abbr": "LA", "SLEPTIM_2009": 7.1337353671514725, "resid_2009": 0.060323147506388064, "SLEPTIM_2020": 7.037752414398596, "resid_2020": 0.0021771403690743355, "var_chng": -0.09598295275287683, "resid_chng": -0.05814600713731373}, {"state_id": 27, "state_abbr": "MN", "SLEPTIM_2009": 7.276561085972851, "resid_2009": 0.11792617407905549, "SLEPTIM_2020": 7.2002024803847124, "resid_2020": 0.10077483890125177, "var_chng": -0.07635860558813867, "resid_chng": -0.01715133517780372}, {"state_id": 56, "state_abbr": "WY", "SLEPTIM_2009": 7.133135578433083, "resid_2009": 0.024919237164882754, "SLEPTIM_2020": 7.123265306122449, "resid_2020": -0.009451321470065712, "var_chng": -0.009870272310633865, "resid_chng": -0.034370558634948464}]}}